navify/__init__.py
navify/drivers/__init__.py
navify/drivers/service_driver.py
navify/drivers/service_mapper.py
navify/drivers/common/__init__.py
navify/drivers/common/deezer/__init__.py
navify/drivers/common/deezer/driver.py
navify/drivers/common/deezer/mapper.py
navify/drivers/common/spotify/__init__.py
navify/drivers/common/spotify/driver.py
navify/drivers/common/spotify/mapper.py
navify/drivers/common/subsonic/__init__.py
navify/drivers/common/subsonic/driver.py
navify/drivers/common/subsonic/mapper.py
navify/drivers/common/youtube/__init__.py
navify/drivers/common/youtube/driver.py
navify/drivers/common/youtube/mapper.py
navify/exceptions/__init__.py
navify/features/__init__.py
navify/features/track_matcher.py
navify/integrations/__init__.py
navify/integrations/musicbrainz.py
navify/models/__init__.py
navify/models/configuration.py
navify/models/playlist.py
navify/models/track.py
navify/utilities/__init__.py
navify/utilities/comparison.py
navify/utilities/normalization.py
navify-1.0.0.dist-info/LICENSE
navify-1.0.0.dist-info/METADATA
navify-1.0.0.dist-info/WHEEL
navify-1.0.0.dist-info/top_level.txt
navify-1.0.0.dist-info/RECORD
