Metadata-Version: 2.1
Name: navify
Version: 1.0.0
Summary: A package to build scripts that interact with various music streaming services.
Author-email: WilliamNT <wntbox@gmail.com>
Project-URL: Homepage, https://github.com/WilliamNT/navify
Project-URL: Issues, https://github.com/WilliamNT/navify/issues
Classifier: Development Status :: 4 - Beta
Classifier: Programming Language :: Python :: 3
Classifier: Operating System :: OS Independent
License-File: LICENSE
Requires-Dist: spotipy
Requires-Dist: py-sonic
Requires-Dist: musicbrainzngs
Requires-Dist: thefuzz
Requires-Dist: streamrip
Requires-Dist: ytmusicapi
Requires-Dist: importlib-metadata; python_version < "3.10"
